CSF.py
_CSF.cp310-win32.pyd
cloth_simulation_filter-1.1.7.dist-info/licenses/LICENSE.txt
cloth_simulation_filter-1.1.7.dist-info/METADATA
cloth_simulation_filter-1.1.7.dist-info/WHEEL
cloth_simulation_filter-1.1.7.dist-info/top_level.txt
cloth_simulation_filter-1.1.7.dist-info/RECORD
