Metadata-Version: 2.4
Name: cloth_simulation_filter
Version: 1.1.7
Summary: CSF: Ground Filtering based on Cloth Simulation
Home-page: http://ramm.bnu.edu.cn/projects/CSF/
Author: Jianbo Qi
Maintainer: Jianbo Qi
Maintainer-email: jianboqi@126.com
License: Apache-2.0
Keywords: LiDAR DTM DSM Classification
License-File: LICENSE.txt
Dynamic: author
Dynamic: description
Dynamic: description-content-type
Dynamic: home-page
Dynamic: keywords
Dynamic: license
Dynamic: license-file
Dynamic: maintainer
Dynamic: maintainer-email
Dynamic: summary
